{"id":"2fc903a6-fe63-42b1-be2c-be0f4877529d","offerInternalName":"Aafaq Human Resources Training And Development Center","offerOrder":0,"offerFeatured":0,"offerImageUri":"/upload/offers/aafaq-human-resources-training-and-development-center-1632992912838.jpg","discount":"30","discountType":"PERCENTAGE","offerExpiry":"2026-09-27T20:00:00Z","offerStatus":2,"offerSlug":"aafaq-human-resources-training-development-center","autoRenew":true,"localData":{"ar":{"description":"\u003cp class=\"ql-align-right ql-direction-rtl\"\u003eالشروط والأحكام :\u003c/p\u003e\u003cp class=\"ql-align-right ql-direction-rtl\"\u003e1.\tتسري العروض علي جميع الدورات التدريبية لمركز آفاق.\u003c/p\u003e\u003cp class=\"ql-align-right ql-direction-rtl\"\u003e2.\tلا يسري هذا العرض بتزامن مع عروض أخرى.\u003c/p\u003e\u003cp class=\"ql-align-right ql-direction-rtl\"\u003e3.\tالعروض لا يمكن تحويلها لأي طرف آخر أو استبدالها نقدا.\u003c/p\u003e\u003cp class=\"ql-align-right ql-direction-rtl\"\u003eللحجز والاستعلام:\u003c/p\u003e\u003cp class=\"ql-align-right ql-direction-rtl\"\u003eدبا الفجيرة ،منطقة الراشدية، خلف مستشفى الشرق الطبي\u003c/p\u003e\u003cp class=\"ql-align-right ql-direction-rtl\"\u003e0\u003ca rel=\"noopener noreferrer\" href=\"tel:092433000\"\u003e92433000\u003c/a\u003e\u003c/p\u003e\u003cp class=\"ql-align-right ql-direction-rtl\"\u003e\u003ca rel=\"noopener noreferrer\" href=\"tel:00971567953704\"\u003e00971567953704\u003c/a\u003e\u003c/p\u003e\u003cp class=\"ql-align-right ql-direction-rtl\"\u003e\u003ca rel=\"noopener noreferrer\" href=\"tel:00971509803067\"\u003e00971509803067\u003c/a\u003e\u003c/p\u003e\u003cp class=\"ql-align-right ql-direction-rtl\"\u003eEmail:\u0026nbsp;info@aafaqcentre.com\u003c/p\u003e\u003cp\u003e\u003cbr\u003e\u003c/p\u003e","shortDescription":"\u003cp class=\"ql-align-right ql-direction-rtl\"\u003eإبرز بطاقة فزعة الصالحة الخاصة بك\u0026nbsp;واستمتع بخصم يصل الى %30 على الفاتورة\u003c/p\u003e\u003cp class=\"ql-align-right ql-direction-rtl\"\u003eفزعة فخر الوطن: %30\u003c/p\u003e\u003cp class=\"ql-align-right ql-direction-rtl\"\u003eفزعة همم : %30\u003c/p\u003e\u003cp class=\"ql-align-right ql-direction-rtl\"\u003e\u0026nbsp;فزعة البلاتينية : %20\u0026nbsp;\u003c/p\u003e\u003cp class=\"ql-align-right ql-direction-rtl\"\u003eفزعة الذهبية: %20\u0026nbsp;\u003c/p\u003e\u003cp class=\"ql-align-right ql-direction-rtl\"\u003eفزعة الفضية: %20\u0026nbsp;\u003c/p\u003e\u003cp class=\"ql-align-right ql-direction-rtl\"\u003eفزعة خصومات: %15\u003c/p\u003e\u003cp\u003e\u003cbr\u003e\u003c/p\u003e","subTitle":"مركز آفاق لتدريب وتنمية الموارد البشرية","title":"خصم يصل إلى 30%"},"en":{"description":"\u003cp\u003eTerms and conditions :\u003c/p\u003e\u003cp\u003e1.\tOffers are valid on all Aafaq training courses\u003c/p\u003e\u003cp\u003e2.\tThis offer is not valid in conjunction with other offers\u003c/p\u003e\u003cp\u003e3.\tOffers cannot transferred to any other party or exchanged for cash\u003c/p\u003e\u003cp\u003e\u003cbr\u003e\u003c/p\u003e\u003cp\u003e\u003cbr\u003e\u003c/p\u003e\u003cp\u003eLocation \u0026amp; contact:\u003c/p\u003e\u003cp\u003edibba fujairah ,Al rashidya , behind Alsharq Medical Hospital\u003c/p\u003e\u003cp\u003e\u003ca rel=\"noopener noreferrer\" href=\"tel:092433000\"\u003e092433000\u003c/a\u003e\u003c/p\u003e\u003cp\u003e\u003ca rel=\"noopener noreferrer\" href=\"tel:00971 567953704\"\u003e00971 567953704\u003c/a\u003e\u003c/p\u003e\u003cp\u003e\u003ca rel=\"noopener noreferrer\" href=\"tel:00971 509803067\"\u003e00971 509803067\u003c/a\u003e\u003c/p\u003e\u003cp\u003eEmail:\u0026nbsp;info@aafaqcentre.com\u003c/p\u003e\u003cp\u003e\u003cbr\u003e\u003c/p\u003e","shortDescription":"\u003cp\u003ePresent your valid Fazaa Card to enjoy up to 30% discount on the bill.\u003c/p\u003e\u003cp\u003eFazaa Front Line Heroes: 30%\u003c/p\u003e\u003cp\u003eFazaa Hemam: 30%\u003c/p\u003e\u003cp\u003eFazaa Platinum: 20%\u003c/p\u003e\u003cp\u003eFazaa Gold: 20%\u003c/p\u003e\u003cp\u003eFazaa Silver: 20%\u003c/p\u003e\u003cp\u003eFazaa Discount: 15%\u003c/p\u003e\u003cp\u003e\u003cbr\u003e\u003c/p\u003e","subTitle":"Aafaq Human Resources Training And Development Center","title":"Up to 30% Discount     "}},"partner":{"id":"485c53b0-1029-4a58-a005-92dfed8c9ecb","partnerDocuments":[{"createdAt":"2021-09-30T13:09:11.567778","description":"Document uploaded on 30/09/21 @ 13:09","fileUri":"/upload/partners/doc-aafaq-human-resources-training-and-development-center-1632992951569.pdf","id":"876c9ab8-ebae-4375-8157-6d05a608cd0e"},{"createdAt":"2021-09-30T13:09:11.568268","description":"Document uploaded on 30/09/21 @ 13:09","fileUri":"/upload/partners/doc-aafaq-human-resources-training-and-development-center-1632992951569.pdf","id":"6f43290d-7da9-4d4e-89c6-0c5231b6c7b6"}],"partnerLink":"https://aafaqcentre.com/","partnerLogoUri":"/upload/partners/aafaq-human-resources-training-and-development-center-1632992208825.jpg","partnerName":"AAFAQ HUMAN RESOURCES TRAINING AND DEVELOPMENT CENTER","partnerNameAr":"مركز آفاق لتدريب وتنمية الموارد البشرية"},"categories":[{"categoryFeatured":1,"categoryHidden":0,"categoryImageUri":"/upload/services/education-1727933078597.svg","categoryInternalName":"Education","categoryOrder":8,"categorySlug":"education","id":"7e7f7532-a50e-4fa9-9acc-093ebbdb3a40","localData":{"ar":{"description":"","name":"التعليم"},"en":{"description":"","name":"Education"}}}],"locations":[{"address":" dibba fujairah Al rashidya , behind Alsharq Medical Hospital","city":"Fujairah","country":"","id":"917fd1c3-daf1-451d-b88b-dd78d2f18fbe","location":{"type":"point","values":"(56.273256910657224,25.594241889310226)","x":56.273256910657224,"y":25.594241889310226},"name":"Aafaq Human Resources Training And Development Center  "}],"images":[{"id":"a569a694-78d3-48ea-8466-aeb9900a243c","imageUri":"/upload/offers/aafaq-human-resources-training-and-development-center-1632992913545.jpg","mainImage":0},{"id":"4abc8fd4-de1e-4f23-8ee4-0f043b8d6f03","imageUri":"/upload/offers/aafaq-human-resources-training-and-development-center-1632992913891.jpg","mainImage":0},{"id":"0f1bf1fb-7988-4a98-9770-5cfa0c20129c","imageUri":"/upload/offers/aafaq-human-resources-training-and-development-center-1632992914247.jpg","mainImage":0},{"id":"e584d60d-ae08-41fe-895e-daaa32b65b6a","imageUri":"/upload/offers/aafaq-human-resources-training-and-development-center-1632992914598.jpg","mainImage":0},{"id":"b6191f99-509b-4a2b-af55-6476f31e7272","imageUri":"/upload/offers/aafaq-human-resources-training-and-development-center-1632992914957.jpg","mainImage":0},{"id":"ff8155b4-e34d-4ec6-b2f3-e4b08c6bb300","imageUri":"/upload/offers/aafaq-human-resources-training-and-development-center-1632992915310.jpg","mainImage":0}],"tiers":[{"discount":"20","id":1,"levelName":"Platinum"},{"discount":"20","id":2,"levelName":"Gold"},{"discount":"20","id":3,"levelName":"Silver"},{"discount":"15","id":4,"levelName":"Discount Membership"}],"companies":[{"companyId":"b0e4757c-bdca-49ce-b4f1-a5a4534410d2","companyName":"HEMAM","tiers":[{"discount":"30","id":4,"levelName":"Discount Membership"}]},{"companyId":"b8d7b422-f393-4e11-9bed-2ae660d99b88","companyName":"Frontline Registration","tiers":[{"discount":"30","id":4,"levelName":"Discount Membership"}]}],"shortUrl":"https://s.fazaa.ae/6eCyHsw"}