{"id":"4db77b2e-33a5-4b78-8274-053eca3a8fe6","offerInternalName":"AL Khoory Courtyard Hotel ","offerOrder":0,"offerFeatured":0,"offerImageUri":"/upload/offers/al-khoory-courtyard-hotel-1669717617875.jpg","discount":"20","discountType":"PERCENTAGE","offerExpiry":"2026-10-10T00:00:00Z","offerStatus":2,"offerSlug":"al-khoory-courtyard-hotel","autoRenew":false,"localData":{"ar":{"description":"\u003cp class=\"ql-align-right ql-direction-rtl\"\u003e\u003cstrong\u003eالشروط والأحكام :\u003c/strong\u003e\u003c/p\u003e\u003cp class=\"ql-align-right ql-direction-rtl\"\u003e• يجب تقديم بطاقة فزعة صالحة\u0026nbsp;\u003c/p\u003e\u003cp class=\"ql-align-right ql-direction-rtl\"\u003e• لا يسري هذا العرض بتزامن مع عروض اخرى\u003c/p\u003e\u003cp class=\"ql-align-right ql-direction-rtl\"\u003e*يطبق الخصم على الحجوزات المباشرة مع الفندق فقط و الاتطبق في حال الحجز عن طريق طرف ثالث.\u003c/p\u003e\u003cp class=\"ql-align-right ql-direction-rtl\"\u003e*الغرف و كافة الخدمات تخضع لتوافر الامكانية.\u003c/p\u003e\u003cp class=\"ql-align-right ql-direction-rtl\"\u003e•لعروض لا يمكن تحويلها لأي طرف آخر أو إستبدالها نقدا.\u003c/p\u003e\u003cp class=\"ql-align-right ql-direction-rtl\"\u003e\u0026nbsp;للحجز والإستعلام : دبي\u003c/p\u003e\u003cp class=\"ql-align-right\"\u003esales5@alkhooryhotels.com \u003c/p\u003e\u003cp class=\"ql-align-right\"\u003e 0551912423\u003c/p\u003e\u003cp class=\"ql-align-right ql-direction-rtl\"\u003e بريد الاكتروني :\u003c/p\u003e\u003cp class=\"ql-align-right\"\u003eالحجوزات المركزية: 0097143146200\u003c/p\u003e\u003cp class=\"ql-align-right ql-direction-rtl\"\u003e\u003cbr\u003e\u003c/p\u003e","shortDescription":"\u003cp class=\"ql-direction-rtl ql-align-right\"\u003eقم بتقديم بطاقة فزعه واستمتع:\u003c/p\u003e\u003cp class=\"ql-direction-rtl ql-align-right\"\u003eخصم 20% على الاسعار الغرف\u003c/p\u003e\u003cp class=\"ql-direction-rtl ql-align-right\"\u003eخصم 20% على المطاعم\u003c/p\u003e","subTitle":"فندق الخوري كورتيارد","title":"استمتع خصم 20% على اسعار الغرف"},"en":{"description":"\u003cp\u003e\u003cstrong style=\"color: rgb(24, 76, 156);\"\u003eTerms and conditions \u003c/strong\u003e\u003c/p\u003e\u003cp\u003e\u003cspan style=\"color: rgb(123, 123, 123);\"\u003eTerms and conditions:\u003c/span\u003e\u003c/p\u003e\u003cp\u003e\u003cspan style=\"color: rgb(123, 123, 123);\"\u003e• To avail the offer a Fazaa member must present a valid Fazaa Card\u003c/span\u003e\u003c/p\u003e\u003cp\u003e\u003cspan style=\"color: rgb(123, 123, 123);\"\u003e• The offers are not valid in conjunction with any other deals or promotions.\u003c/span\u003e\u003c/p\u003e\u003cp\u003e\u003cspan style=\"color: rgb(123, 123, 123);\"\u003e*The discount is applicable for booking made directly with the hotel not via third party.\u003c/span\u003e\u003c/p\u003e\u003cp\u003e\u003cspan style=\"color: rgb(123, 123, 123);\"\u003e*ٌRooms \u0026amp; other services are subject to availability.\u003c/span\u003e\u003c/p\u003e\u003cp\u003eLocation \u0026amp; Contact:\u003c/p\u003e\u003cp\u003eDubai – AL Waha Street, Exit 45 off Sheikh Zayed Road,\u003c/p\u003e\u003cp\u003ebehind Oasis Mall\u003c/p\u003e\u003cp\u003esales5@alkhooryhotels.com \u003c/p\u003e\u003cp\u003e 0551912423\u003c/p\u003e\u003cp\u003e\u003cspan style=\"color: rgb(123, 123, 123);\"\u003eCentral reservation: +97143146200\u003c/span\u003e\u003c/p\u003e\u003cp\u003e\u003cspan style=\"color: rgb(123, 123, 123);\"\u003eEmail: \u003c/span\u003e\u003ca href=\"mailto:reservations@alkhooryhotels.com\" rel=\"noopener noreferrer\" target=\"_blank\"\u003ereservations@alkhooryhotels.com\u003c/a\u003e\u003c/p\u003e","shortDescription":"\u003cp\u003ePresent your valid Fazaa Card to enjoy:\u003c/p\u003e\u003cp\u003e·\u0026nbsp;\u0026nbsp;\u0026nbsp;\u0026nbsp;\u0026nbsp;\u0026nbsp;\u0026nbsp;\u0026nbsp;20% Discount on Room rates.\u003c/p\u003e\u003cp\u003e·\u0026nbsp;\u0026nbsp;\u0026nbsp;\u0026nbsp;\u0026nbsp;\u0026nbsp;\u0026nbsp;\u0026nbsp;20% Discount on Restaurants\u003c/p\u003e","subTitle":"AL Khoory Courtyard Hotel ","title":"Enjoy 20% discount on Room rates"}},"partner":{"id":"30c9fef8-74b8-40f6-bd09-bef6c68449a5","partnerDocuments":null,"partnerLink":"www.alkhooryhotels.com","partnerLogoUri":"/upload/partners/al-khoory-courtyard-hotel-1669717298435.jpg","partnerName":"AL Khoory Courtyard Hotel ","partnerNameAr":"فندق الخوري كورتيارد"},"categories":[{"categoryFeatured":1,"categoryHidden":0,"categoryImageUri":"/upload/services/exclusive-offers-1727933620577.svg","categoryInternalName":"Exclusive Offers","categoryOrder":0,"categorySlug":"exclusive-offers","id":"674c0877-7b83-4b4b-8f9a-2ebd441dc02e","localData":{"ar":{"description":"","name":"العروض الحصرية"},"en":{"description":"","name":"Exclusive Offers"}}},{"categoryFeatured":1,"categoryHidden":0,"categoryImageUri":"/upload/services/hotels-resorts-1727933152505.svg","categoryInternalName":"Hotels \u0026 Resorts","categoryOrder":4,"categorySlug":"hotel-and-resorts","id":"81de8860-67b8-4357-8ce5-e0b0e91309eb","localData":{"ar":{"description":"","name":"فنادق ومنتجعات"},"en":{"description":"","name":"Hotels \u0026 Resorts"}}}],"locations":[{"address":"AL Waha Street Exit 45 off Sheikh Zayed Road behind Oasis Mall","city":"Dubai","cityId":"37eee491-ca93-4277-905d-8ea5b073c572","country":"","id":"7c3ff86a-d0d2-474d-a67e-7d6d6240b2b2","location":{"type":"point","values":"(55.24891,25.16206)","x":55.24891,"y":25.16206},"name":"Al Khoory Courtyard Hotel"}],"images":[{"id":"8e003e89-19c1-405b-8663-ee4b069639b9","imageUri":"/upload/offers/al-khoory-courtyard-hotel-1669717620055.jpg","mainImage":0},{"id":"3ba45ec3-68f7-46d8-ae14-e9d35e9af75f","imageUri":"/upload/offers/al-khoory-courtyard-hotel-1669717620416.jpg","mainImage":0},{"id":"c54c84c8-9161-4fa8-9307-db799f242e11","imageUri":"/upload/offers/al-khoory-courtyard-hotel-1669717620825.jpg","mainImage":0},{"id":"b3072ed7-00be-4496-94bd-ad33c3aa1c2b","imageUri":"/upload/offers/al-khoory-courtyard-hotel-1669717621250.jpg","mainImage":0},{"id":"674cbce4-0e38-4f74-8831-13258540e667","imageUri":"/upload/offers/al-khoory-courtyard-hotel-1669717621600.jpg","mainImage":0},{"id":"eb238f73-9606-43e5-9b55-be934bfd5a04","imageUri":"/upload/offers/al-khoory-courtyard-hotel-1669717623386.jpg","mainImage":0}],"tiers":[],"companies":[],"shortUrl":"https://s.fazaa.ae/qnG8rhT"}