{"id":"6605c1f7-22fd-4b39-848c-f7d133935835","offerInternalName":"GLOWLAND","offerOrder":0,"offerFeatured":0,"offerImageUri":"/upload/offers/glowland-1669782439622.jpg","discount":"20","discountType":"PERCENTAGE","offerExpiry":"2026-11-16T10:00:00.434183Z","offerStatus":2,"offerSlug":"glowland","autoRenew":true,"localData":{"ar":{"description":"\u003cp class=\"ql-align-right ql-direction-rtl\"\u003eالشروط والأحكام :\u003c/p\u003e\u003cp class=\"ql-align-right ql-direction-rtl\"\u003e- العرض غير سارٍ في وقت الإجازات والمناسبات الرسمية\u003c/p\u003e\u003cp class=\"ql-align-right ql-direction-rtl\"\u003e- العرض يكون سارٍ في الإجازة الرسمية أيام نهاية الأسبوع\u003c/p\u003e\u003cp class=\"ql-align-right ql-direction-rtl\"\u003e- تطبق الشروط و الأحكام لكل عرض\u003c/p\u003e\u003cp class=\"ql-align-right ql-direction-rtl\"\u003e- يسري العرض على أعضاء فزعة + 6 (ستة) ضيوف\u003c/p\u003e\u003cp class=\"ql-align-right ql-direction-rtl\"\u003e- يجب عليك الإستظهار ببطاقة فزعة صالحة للاستفادة من العرض\u003c/p\u003e\u003cp class=\"ql-align-right ql-direction-rtl\"\u003e- هذا العرض لا يطبق بالتزامن مع أي عرض مقدم آخر\u003c/p\u003e\u003cp class=\"ql-align-right ql-direction-rtl\"\u003e- لا يمكن استبدال الخصم نقدا\u003c/p\u003e\u003cp class=\"ql-align-right ql-direction-rtl\"\u003e\u003cbr\u003e\u003c/p\u003e\u003cp class=\"ql-align-right ql-direction-rtl\"\u003eللحجز والاستعلام :\u003c/p\u003e\u003cp class=\"ql-align-right ql-direction-rtl\"\u003eغلولاند , دبي فيستيفال سيتي مول,الطابق الثاني, دبي,\u003c/p\u003e\u003cp class=\"ql-align-right ql-direction-rtl\"\u003e+971553679463\u0026nbsp;\u003c/p\u003e","shortDescription":"\u003cp class=\"ql-align-right ql-direction-rtl\"\u003eإبرز بطاقة فزعة الصالحة الخاصة بك واستمتع بخصم يصل إلى 20% على الفاتورة\u0026nbsp;\u003c/p\u003e\u003cp class=\"ql-align-right ql-direction-rtl\"\u003eفزعة البلاتينية 20%\u0026nbsp;\u003c/p\u003e\u003cp class=\"ql-align-right ql-direction-rtl\"\u003eفزعة الذهبية 15%\u003c/p\u003e\u003cp class=\"ql-align-right ql-direction-rtl\"\u003eفزعة الفضية 15%\u003c/p\u003e\u003cp class=\"ql-align-right ql-direction-rtl\"\u003eفزعة خصومات 15%\u003c/p\u003e\u003cp class=\"ql-align-right ql-direction-rtl\"\u003e\u003cbr\u003e\u003c/p\u003e","subTitle":"غلولاند","title":"خصم يصل الى 20%"},"en":{"description":"\u003cp\u003eTerms and conditions\u0026nbsp;\u003c/p\u003e\u003cp\u003e- Discount not valid on public Holidays \u0026amp; Special occasions\u003c/p\u003e\u003cp\u003e- Offer valid in public Holiday is on weekend\u003c/p\u003e\u003cp\u003e- Individual Brand Terms and conditions apply\u003c/p\u003e\u003cp\u003e- Offer valid for Fazaa members + 6(six) guests\u003c/p\u003e\u003cp\u003e- The employee must present a valid Fazaa card to avail the offer\u003c/p\u003e\u003cp\u003e- Not valid in conjunction with any other discounts, promotions offers or events\u003c/p\u003e\u003cp\u003e- Discount can’t be redeemed against cash\u003c/p\u003e\u003cp\u003e\u003cbr\u003e\u003c/p\u003e\u003cp\u003eContact \u0026amp; Location:\u003c/p\u003e\u003cp\u003eDubai, GLOWLAND,Dubai Festival City Mall, Second Floor, Dubai – +971553679463\u0026nbsp;\u003c/p\u003e","shortDescription":"\u003cp\u003ePresent your valid Fazaa Card to enjoy up to 20% discount on the bill\u003c/p\u003e\u003cp\u003ePlatinum Fazaa 20%\u003c/p\u003e\u003cp\u003eGolden Fazaa 15%\u003c/p\u003e\u003cp\u003eSilver Fazaa 15%\u003c/p\u003e\u003cp\u003eFazaa discount 15% discount\u003c/p\u003e\u003cp\u003e\u003cbr\u003e\u003c/p\u003e","subTitle":"GLOWLAND","title":"Up to 20% Discoumt"}},"partner":{"id":"3fcd6c87-cf59-4690-b45b-ac223c2a3fe0","partnerDocuments":[{"createdAt":"2022-11-30T08:26:27.895934","description":"Document uploaded on 30/11/22 @ 08:26","fileUri":"/upload/partners/doc-glowland-1669782387897.docx","id":"7f84f019-3256-4ecb-b5a1-a11f40f9f86a"},{"createdAt":"2022-11-30T08:26:27.89596","description":"Document uploaded on 30/11/22 @ 08:26","fileUri":"/upload/partners/doc-glowland-1669782387961.pdf","id":"0393cffa-174e-4d05-9bc6-7ca447b2432f"}],"partnerLink":"https://www.fazaa.ae/","partnerLogoUri":"/upload/partners/glowland-1669712655108.jpg","partnerName":"GLOWLAND","partnerNameAr":"غلولاند"},"categories":[{"categoryFeatured":1,"categoryHidden":0,"categoryImageUri":"/upload/services/entertainment-1727932040101.svg","categoryInternalName":"Entertainment","categoryOrder":180000,"categorySlug":"entertainment","id":"aea67725-c3ce-4fa0-bd90-2ca3a656b4bc","localData":{"ar":{"description":"الترفيه","name":"الترفيه"},"en":{"description":"","name":"Entertainment"}}}],"locations":[{"address":" 69C2+VQC - مدينة مهرجان دبي - دبي فيستيفال سيتي - دبي","city":"Dubai","cityId":"37eee491-ca93-4277-905d-8ea5b073c572","country":"","id":"12904848-3510-4424-914f-85872bfe62d6","location":{"type":"point","values":"(55.351962,25.222829)","x":55.351962,"y":25.222829},"name":"Food Court Festival City Mall"}],"images":[{"id":"51dd3b1d-b6f0-446b-b50f-35efd87b7a31","imageUri":"/upload/offers/glowland-1669782440633.jpg","mainImage":0},{"id":"1cf93977-7ea5-4a92-8e7a-70a9e69f089e","imageUri":"/upload/offers/glowland-1669782441131.jpg","mainImage":0},{"id":"15a28296-3237-4778-a309-ad854f3d289a","imageUri":"/upload/offers/glowland-1669782441615.jpg","mainImage":0},{"id":"9030e780-f147-4715-890b-f44ff7bdce28","imageUri":"/upload/offers/glowland-1669782442132.jpg","mainImage":0},{"id":"39d77582-5d0c-4d54-8423-e0f89913ad73","imageUri":"/upload/offers/glowland-1669782442620.jpg","mainImage":0}],"tiers":[{"discount":"20","id":1,"levelName":"Platinum"},{"discount":"15","id":2,"levelName":"Gold"},{"discount":"15","id":3,"levelName":"Silver"},{"discount":"15","id":4,"levelName":"Discount Membership"}],"companies":[],"shortUrl":"https://s.fazaa.ae/36atXn2"}