{"id":"0eb8f84f-7e91-4a4d-8828-0674863aae5a","offerInternalName":"Hook Cafe","offerOrder":0,"offerFeatured":0,"offerImageUri":"/upload/offers/hook-cafe-1704872136546.jpg","discount":"15","discountType":"PERCENTAGE","offerExpiry":"2027-01-16T10:00:01.488391Z","offerStatus":2,"offerSlug":"hook-cafe","autoRenew":true,"localData":{"ar":{"description":"\u003cp class=\"ql-direction-rtl ql-align-right\"\u003eالشروط والأحكام :\u003c/p\u003e\u003cp class=\"ql-direction-rtl ql-align-right\"\u003e• يجب تقديم بطاقة فزعة الصالحة للحصول على الخصم.\u003c/p\u003e\u003cp class=\"ql-direction-rtl ql-align-right\"\u003e• لا يسري هذا العرض بالتزامن مع العروض اخرى.\u003c/p\u003e\u003cp class=\"ql-direction-rtl ql-align-right\"\u003eخصم 15%على فاتورة بحد ادني 100 درهم\u003c/p\u003e\u003cp class=\"ql-direction-rtl ql-align-right\"\u003eللحجز والإستعلام : أم القيوين\u0026nbsp;\u003c/p\u003e\u003cp class=\"ql-direction-rtl ql-align-right\"\u003eفلج المعلا – أم القيوين\u0026nbsp;\u003c/p\u003e\u003cp class=\"ql-direction-rtl ql-align-right\"\u003e0585447177\u003c/p\u003e\u003cp\u003e\u003cbr\u003e\u003c/p\u003e","shortDescription":"\u003cp class=\"ql-direction-rtl ql-align-right\"\u003eإبرز بطاقة فزعة الصالحة الخاصة بك واستمتع بخصم %15 على الفاتورة.\u003c/p\u003e\u003cp\u003e\u003cbr\u003e\u003c/p\u003e","subTitle":"هووك كافيه ","title":"خصم 15%"},"en":{"description":"\u003cp\u003eTerms and conditions\u0026nbsp;\u003c/p\u003e\u003cp\u003e• To avail the offer a Fazaa member must present a valid Fazaa Card\u003c/p\u003e\u003cp\u003e• The offers are not valid in conjunction with any other deals or promotions\u003c/p\u003e\u003cp\u003e• 15% with minimum purchease 100AED\u003c/p\u003e\u003cp\u003e\u003cbr\u003e\u003c/p\u003e\u003cp\u003e\u003cbr\u003e\u003c/p\u003e\u003cp\u003eLocation \u0026amp; contact:\u0026nbsp;\u003c/p\u003e\u003cp\u003eFalaj Al Mualla - Umm Al Quwain\u003c/p\u003e\u003cp\u003e058 544 7177\u003c/p\u003e\u003cp\u003e\u003cbr\u003e\u003c/p\u003e\u003cp\u003e\u003cbr\u003e\u003c/p\u003e\u003cp\u003e\u003cbr\u003e\u003c/p\u003e","shortDescription":"\u003cp\u003ePresent your valid Fazaa Card to enjoy a 15% discount on the bill.\u003c/p\u003e\u003cp\u003e\u003cbr\u003e\u003c/p\u003e","subTitle":"Hook Cafe","title":"15%"}},"partner":{"id":"726c67a9-34e4-46e0-a40c-5f9cf7143c7f","partnerDocuments":[{"createdAt":"2021-05-09T12:11:46.214147","description":"Document uploaded on 09/05/21 @ 12:10","fileUri":"/upload/partners/doc-hook-cafe-1620547906215.pdf","id":"3f0262b6-6ea6-445e-b518-714420e128b9"},{"createdAt":"2021-05-09T12:11:46.214161","description":"Document uploaded on 09/05/21 @ 12:11","fileUri":"/upload/partners/doc-hook-cafe-1620547906216.docx","id":"0c8c1856-7571-4129-8468-6fbe58bd0923"}],"partnerLink":"https://www.instagram.com/hook.ae/","partnerLogoUri":"/upload/partners/hook-cafe-1620547813885.jpg","partnerName":"Hook Cafe","partnerNameAr":"هووك كافيه "},"categories":[{"categoryFeatured":1,"categoryHidden":0,"categoryImageUri":"/upload/services/restaurant-cafe-1727932422920.svg","categoryInternalName":"Restaurant \u0026 Cafe","categoryOrder":170000,"categorySlug":"dining","id":"151be776-48c8-4bcc-9040-19aa9210f314","localData":{"ar":{"description":"","name":"المطاعم"},"en":{"description":"","name":"Restaurant \u0026 Cafe"}}}],"locations":[{"address":"Al Nabgghah - Umm Al Quawain","city":"Umm Al Quawain","country":"","id":"63caba2c-8129-46f6-a168-41e99f725a3e","location":{"type":"point","values":"(55.8551487,25.3511753)","x":55.8551487,"y":25.3511753},"name":"Hook Cafe"}],"images":[{"id":"e5ff30d7-e2eb-4418-9881-ed6a0bad2f26","imageUri":"/upload/offers/hook-cafe-1620548699858.jpg","mainImage":0},{"id":"1729e148-318e-4319-8cb0-477699d8c419","imageUri":"/upload/offers/hook-cafe-1620548700243.jpg","mainImage":0},{"id":"1b8aaffd-0d74-4928-817c-ad35af37144f","imageUri":"/upload/offers/hook-cafe-1620548700610.jpg","mainImage":0},{"id":"63e5cc5f-debf-4381-9778-a80d37d9bc7f","imageUri":"/upload/offers/hook-cafe-1620548700987.jpg","mainImage":0},{"id":"7fcdeb34-3f21-46fa-805f-67ece5a53074","imageUri":"/upload/offers/hook-cafe-1620548701373.jpg","mainImage":0},{"id":"5c476f6e-ef6e-4b7d-934e-9ea748e5db43","imageUri":"/upload/offers/hook-cafe-1620548701755.jpg","mainImage":0},{"id":"cd71b130-31f8-44ca-a924-7efa359b50e8","imageUri":"/upload/offers/hook-cafe-1620548702142.jpg","mainImage":0},{"id":"366f0d27-3678-42bd-a4cb-6c6821dc700c","imageUri":"/upload/offers/hook-cafe-1620548702540.jpg","mainImage":0},{"id":"2211d55a-f84f-4219-864a-e93cbf8dbaf6","imageUri":"/upload/offers/hook-cafe-1620548702912.jpg","mainImage":0},{"id":"bed1e790-5461-4f45-9187-f2998175e6d3","imageUri":"/upload/offers/hook-cafe-1620548703350.jpg","mainImage":0},{"id":"6b385223-c1af-486c-97c1-f56ffd11a165","imageUri":"/upload/offers/hook-cafe-1620548703809.jpg","mainImage":0},{"id":"085509d0-683e-45c4-aab7-a5c25ec02b79","imageUri":"/upload/offers/hook-cafe-1620548704481.jpg","mainImage":0},{"id":"8d060652-c5ce-4892-901d-d668c57452c3","imageUri":"/upload/offers/hook-cafe-1620548704892.jpg","mainImage":0},{"id":"d9d44a9e-1385-4d99-b5c9-cde2684793b4","imageUri":"/upload/offers/hook-cafe-1704872137464.jpg","mainImage":0}],"tiers":[],"companies":[],"shortUrl":"https://s.fazaa.ae/tSsHYNG"}